puente/__init__.py
puente/commands.py
puente/ext.py
puente/extract.py
puente/settings.py
puente/utils.py
puente/management/__init__.py
puente/management/commands/__init__.py
puente/management/commands/extract.py
puente/management/commands/merge.py
tests/__init__.py
tests/test_ext.py
tests/test_extract.py
tests/test_merge.py
tests/test_utils.py
puente-1.0.0.dist-info/AUTHORS.rst
puente-1.0.0.dist-info/LICENSE
puente-1.0.0.dist-info/METADATA
puente-1.0.0.dist-info/WHEEL
puente-1.0.0.dist-info/entry_points.txt
puente-1.0.0.dist-info/top_level.txt
puente-1.0.0.dist-info/zip-safe
puente-1.0.0.dist-info/RECORD
