Metadata-Version: 2.1
Name: puente
Version: 1.0.0
Summary: Strings extraction and other tools -- UNMAINTAINED
Home-page: https://github.com/mozilla/puente
Author: Will Kahn-Greene
Author-email: willkg@mozilla.com
License: BSD
Platform: UNKNOWN
Classifier: Development Status :: 2 - Pre-Alpha
Classifier: Framework :: Django
Classifier: Intended Audience :: Developers
Classifier: License :: OSI Approved :: BSD License
Classifier: Natural Language :: English
Classifier: Programming Language :: Python :: 3.7
Classifier: Programming Language :: Python :: 3.8
Classifier: Programming Language :: Python :: 3.9
Classifier: Programming Language :: Python :: 3.10
License-File: LICENSE
License-File: AUTHORS.rst
Requires-Dist: Babel (>=2.1.1)
Requires-Dist: Jinja2 (>=2.7)
Requires-Dist: markupsafe
Requires-Dist: Django (<4.0.0,>=3.2.0)
